gitcmd/__init__.py
gitcmd-1.1.1.dist-info/DESCRIPTION.rst
gitcmd-1.1.1.dist-info/METADATA
gitcmd-1.1.1.dist-info/RECORD
gitcmd-1.1.1.dist-info/WHEEL
gitcmd-1.1.1.dist-info/metadata.json
gitcmd-1.1.1.dist-info/top_level.txt
