Metadata-Version: 2.0
Name: gitcmd
Version: 1.1.1
Summary: a wrapper of git command
Home-page: https://github.com/philoprove/gitcmd
Author: Kenny Zhang
Author-email: sphy@foxmail.com
License: MIT
Keywords: git gitlab github
Platform: UNKNOWN
Classifier: Development Status :: 3 - Alpha
Classifier: Intended Audience :: Developers
Classifier: Environment :: Console
Classifier: Topic :: Software Development :: Build Tools
Classifier: License :: OSI Approved :: MIT License
Classifier: Programming Language :: Python :: 2
Classifier: Programming Language :: Python :: 2.7
Requires-Dist: pexpect
